QtSLIX/ClusterWidget.py
QtSLIX/ImageWidget.py
QtSLIX/MainWindow.py
QtSLIX/ParameterGeneratorWidget.py
QtSLIX/VisualizationWidget.py
QtSLIX/__init__.py
QtSLIX/ThreadWorkers/ParameterGenerator.py
QtSLIX/ThreadWorkers/Visualization.py
QtSLIX/ThreadWorkers/__init__.py
QtSLIX/_cmd/__init__.py
QtSLIX/_cmd/main.py
tests/__init__.py
tests/test_imagewidget.py
QtSLIX-1.0.2.dist-info/LICENSE
QtSLIX-1.0.2.dist-info/METADATA
QtSLIX-1.0.2.dist-info/WHEEL
QtSLIX-1.0.2.dist-info/entry_points.txt
QtSLIX-1.0.2.dist-info/top_level.txt
QtSLIX-1.0.2.dist-info/RECORD
