Metadata-Version: 2.1
Name: QtSLIX
Version: 1.0.2
Summary: QtSLIX is an expansion to the Scattered Light Imaging ToolboX by adding a graphical user interface.
Home-page: https://github.com/3d-pli/QtSLIX
Author: Jan Andre Reuter
Author-email: j.reuter@fz-juelich.de
License: MIT
Platform: UNKNOWN
Classifier: Programming Language :: Python :: 3
Classifier: License :: OSI Approved :: MIT License
Classifier: Operating System :: OS Independent
Requires-Python: >=3.6
License-File: LICENSE
Requires-Dist: PyQt5
Requires-Dist: matplotlib
Requires-Dist: numpy
Requires-Dist: SLIX (>=2.4.0)
